snapshot_field/__init__.py
snapshot_field/apps.py
snapshot_field/compat.py
snapshot_field/fields.py
snapshot_field/monkey.py
snapshot_field/utils.py
django_snapshot_field-0.1.5.dist-info/LICENSE
django_snapshot_field-0.1.5.dist-info/METADATA
django_snapshot_field-0.1.5.dist-info/WHEEL
django_snapshot_field-0.1.5.dist-info/top_level.txt
django_snapshot_field-0.1.5.dist-info/RECORD
